{"guide_faq.md":"79254e2b","guide_css.md":"db5fc79d","guide_public.md":"84526512","guide_directory-structure.md":"f0919b75","guide_plugin.md":"7d7f4c03","guide_builder.md":"7aef2181","guide_config.md":"62eccd9f","guide_getting-started.md":"c6c982dc","guide_upgrade3.md":"3bcfb370","guide_mock.md":"8a0d04da","guide_env.md":"7d08abd8","guide_index.md":"d93ea205","index.md":"61de269f","guide_image.md":"2e74f65f","reference_plugin_index.md":"ee42a061","reference_plugin_dev_index.md":"1a7b2210","reference_api_index.md":"72b9ecff","guide_contributing.md":"8666fd37","reference_cli_index.md":"4ef9c410","reference_api.md":"5e62d83f","reference_plugin_plugins_icon.md":"f2cb3f94","reference_plugin_plugins_jest.md":"d574f7ac","reference_plugin_dev_api.md":"2d7e42be","guide_template.md":"0f61d40d","reference_plugin_plugins_access.md":"ba03251a","reference_plugin_plugins_pinia.md":"c7ff2416","reference_plugin_plugins_locale.md":"e5f16382","reference_plugin_plugins_layout.md":"5c7c196b","guide_runtime-config.md":"8d7d4f16","guide_route.md":"11dd4240","reference_plugin_plugins_editor.md":"59115d8d","reference_plugin_plugins_enums.md":"9c0c3064","reference_config_index.md":"94262ec5","reference_plugin_plugins_login.md":"c4b18ed3","reference_plugin_plugins_model.md":"ef7fdf24","reference_plugin_plugins_windicss.md":"8deb5ce9","reference_plugin_plugins_sass.md":"aea91d6e","reference_plugin_plugins_watermark.md":"95337b01","reference_plugin_plugins_qiankun.md":"ec18784c","reference_plugin_plugins_vuex.md":"3806c06f","reference_plugin_plugins_swc.md":"f887c1f1","reference_plugin_plugins_request-4.md":"58780b87","reference_plugin_plugins_request.md":"a62289a7"}
